{"data":{"_id":6000,"properties":{"uuid":{"name":"uuid","kind":"scalar","primary":true,"type":"uuid","fieldNames":["giveaway_uuid"],"array":false,"runtimeType":"string"},"createtime":{"name":"createtime","kind":"scalar","type":"Date","getter":false,"setter":false,"fieldNames":["giveaway_createtime"],"array":false,"runtimeType":"Date"},"updatetime":{"name":"updatetime","kind":"scalar","type":"Date","getter":false,"setter":false,"fieldNames":["giveaway_updatetime"],"array":false,"runtimeType":"Date"},"giveaway_giftcarduuid":{"name":"giveaway_giftcarduuid","kind":"scalar","type":"uuid","nullable":false,"getter":false,"setter":false,"array":false,"runtimeType":"string"},"giveaway_begindate":{"name":"giveaway_begindate","kind":"scalar","nullable":false,"getter":false,"setter":false,"type":"Date","array":false,"runtimeType":"Date"},"giveaway_enddate":{"name":"giveaway_enddate","kind":"scalar","nullable":false,"getter":false,"setter":false,"type":"Date","array":false,"runtimeType":"Date"},"giveaway_number":{"name":"giveaway_number","kind":"scalar","nullable":true,"getter":false,"setter":false,"type":"number","array":false,"runtimeType":"number","optional":true}},"primaryKeys":["uuid"],"filters":{},"hooks":{},"indexes":[],"uniques":[],"className":"Giveaway","path":"./src/entities/giveaway.entity.ts","collection":"giveaway","name":"Giveaway","abstract":false,"internal":true,"constructorParams":["giveaway_giftcarduuid","giveaway_begindate","giveaway_enddate","giveaway_number"],"toJsonParams":[],"extends":"BaseEntity","useCache":true,"compositePK":false,"simplePK":true},"origin":"./src/entities/giveaway.entity.ts","hash":"83b0b40ae19249f73993dec452245158","version":"6.4.15"}
